PyCHZZK/__init__.py
PyCHZZK/_http.py
PyCHZZK/api.py
PyCHZZK/utils.py
PyCHZZK/enums/__init__.py
PyCHZZK/enums/fields.py
PyCHZZK/exceptions/__init__.py
pychzzk-0.1.2.dist-info/LICENSE
pychzzk-0.1.2.dist-info/WHEEL
pychzzk-0.1.2.dist-info/METADATA
pychzzk-0.1.2.dist-info/RECORD
