Metadata-Version: 2.1
Name: PyCHZZK
Version: 0.1.2
Summary: NAVER CHZZK Python SDK
Author-email: Netchive <opensource@netchive.com>
Maintainer-email: Euiseo Cha <zeroday0619_dev@outlook.com>
Requires-Python: >=3.10
Classifier: License :: OSI Approved :: MIT License
Requires-Dist: httpx==0.27.0
Project-URL: Source, https://github.com/Netchive/PyCHZZK
